pushable/__init__.py
pushable/pushable.py
pushable/py.typed
pushable-0.1.8.dist-info/LICENSE
pushable-0.1.8.dist-info/METADATA
pushable-0.1.8.dist-info/WHEEL
pushable-0.1.8.dist-info/RECORD
